serialhub/__init__.py
serialhub/_frontend.py
serialhub/_version.py
serialhub/backend.py
serialhub/serialio.py
serialhub/labextension/build_log.json
serialhub/labextension/package.json
serialhub/labextension/static/lib_index_js.860159e25d6f0b4ab178.js
serialhub/labextension/static/lib_index_js.860159e25d6f0b4ab178.js.map
serialhub/labextension/static/lib_plugin_js.73f4fb8c50aeae500020.js
serialhub/labextension/static/lib_plugin_js.73f4fb8c50aeae500020.js.map
serialhub/labextension/static/lib_widget_js.fd6f21af19df40826804.js
serialhub/labextension/static/lib_widget_js.fd6f21af19df40826804.js.map
serialhub/labextension/static/node_modules_css-loader_dist_cjs_js_style_base_css-node_modules_style-loader_dist_runtime_inj-ec3a80.5a4b73a13eda467e5cc7.js
serialhub/labextension/static/node_modules_css-loader_dist_cjs_js_style_base_css-node_modules_style-loader_dist_runtime_inj-ec3a80.5a4b73a13eda467e5cc7.js.map
serialhub/labextension/static/remoteEntry.c66315420c7993e47f6a.js
serialhub/labextension/static/remoteEntry.c66315420c7993e47f6a.js.map
serialhub/labextension/static/style.js
serialhub/labextension/static/style_index_js.f5573d09ae73e317fcdb.js
serialhub/labextension/static/style_index_js.f5573d09ae73e317fcdb.js.map
serialhub/nbextension/__init__.py
serialhub/nbextension/static/extension.js
serialhub/tests/__init__.py
serialhub/tests/conftest.py
serialhub/tests/test_backend.py
serialhub/tests/test_nbextension_path.py
serialhub/tests/test_serialhub.py
serialhub/tests/test_serialio.py
serialhub-0.0.37.data/data/etc/jupyter/jupyter_notebook_config.d/serialhub.json
serialhub-0.0.37.data/data/etc/jupyter/jupyter_server_config.d/serialhub.json
serialhub-0.0.37.data/data/etc/jupyter/nbconfig/notebook.d/serialhub.json
serialhub-0.0.37.data/data/share/jupyter/labextensions/serialhub/build_log.json
serialhub-0.0.37.data/data/share/jupyter/labextensions/serialhub/install.json
serialhub-0.0.37.data/data/share/jupyter/labextensions/serialhub/package.json
serialhub-0.0.37.dist-info/LICENSE.txt
serialhub-0.0.37.dist-info/METADATA
serialhub-0.0.37.dist-info/WHEEL
serialhub-0.0.37.dist-info/top_level.txt
serialhub-0.0.37.dist-info/RECORD
